lazo/__cli__.py
lazo/__init__.py
lazo/cli.py
lazo/clients.py
lazo/exceptions.py
lazo/objects.py
lazo/out.py
lazo/params.py
lazo/rancher.py
lazo/types.py
lazo/utils.py
lazo-2.0.2.dist-info/entry_points.txt
lazo-2.0.2.dist-info/WHEEL
lazo-2.0.2.dist-info/METADATA
lazo-2.0.2.dist-info/RECORD
