Metadata-Version: 2.1
Name: lazo
Version: 2.0.2
Summary: lazo
Home-page: https://github.com/saxix/lazo
Keywords: docker,rancher
Author: sax
Author-email: s.apostolico@gmail.com
Requires-Python: >=3.8
Classifier: Development Status :: 3 - Alpha
Classifier: Environment :: Console
Classifier: Intended Audience :: Developers
Classifier: Intended Audience :: System Administrators
Classifier: License :: OSI Approved :: MIT License
Classifier: Programming Language :: Python :: 3
Classifier: Programming Language :: Python :: 3.8
Classifier: Programming Language :: Python :: 3.9
Classifier: Programming Language :: Python :: 3.10
Requires-Dist: click
Requires-Dist: colorama
Requires-Dist: pygments
Requires-Dist: requests
Requires-Dist: websocket-client
Project-URL: Repository, https://github.com/saxix/lazo
